sparv_bert_neighbour/__init__.py
sparv_bert_neighbour_plugin-0.2.1.dist-info/METADATA
sparv_bert_neighbour_plugin-0.2.1.dist-info/WHEEL
sparv_bert_neighbour_plugin-0.2.1.dist-info/entry_points.txt
sparv_bert_neighbour_plugin-0.2.1.dist-info/licenses/LICENSE
sparv_bert_neighbour_plugin-0.2.1.dist-info/RECORD
